viscars/__init__.py
viscars/dao/__init__.py
viscars/evaluation/__init__.py
viscars/evaluation/evaluators/__init__.py
viscars/evaluation/evaluators/base.py
viscars/evaluation/evaluators/factory.py
viscars/evaluation/evaluators/kfoldcv.py
viscars/evaluation/evaluators/loocv.py
viscars/evaluation/metrics/__init__.py
viscars/evaluation/metrics/factory.py
viscars/evaluation/metrics/metrics.py
viscars/namespace/__init__.py
viscars/namespace/dashboard.owl
viscars/recommenders/__init__.py
viscars/recommenders/base.py
viscars/recommenders/cacf.py
viscars/recommenders/cf.py
viscars/recommenders/factory.py
viscars/recommenders/fastppr.py
viscars/recommenders/mf.py
viscars/recommenders/pagerank.py
viscars/recommenders/ppr.py
viscars/recommenders/random_.py
viscars/recommenders/similarity/__init__.py
viscars/recommenders/similarity/factory.py
viscars/recommenders/similarity/rdf2vec.py
viscars/recommenders/similarity/weisfeilerlehman.py
viscars/requirements.txt
viscars/training/gridsearchcv.py
viscars/utils/__init__.py
viscars-1.0.2.dist-info/LICENSE
viscars-1.0.2.dist-info/METADATA
viscars-1.0.2.dist-info/WHEEL
viscars-1.0.2.dist-info/RECORD
