Metadata-Version: 2.1
Name: VisCARS
Version: 1.0.2
Summary: VisCARS: Knowledge Graph-based Context-Aware Recommender System for Visualizations
Home-page: https://github.com/predict-idlab/VisCARS
Keywords: recommender system,visualizations,context-aware
Author: Pieter Moens
Author-email: pieter.moens@ugent.be
Requires-Python: >=3.9,<4.0
Classifier: Operating System :: MacOS :: MacOS X
Classifier: Operating System :: Microsoft :: Windows
Classifier: Operating System :: POSIX :: Linux
Classifier: Programming Language :: Python
Classifier: Programming Language :: Python :: 3
Classifier: Programming Language :: Python :: 3.9
Classifier: Programming Language :: Python :: 3.10
Classifier: Programming Language :: Python :: 3.11
Classifier: Programming Language :: Python :: 3.12
Classifier: Programming Language :: Python :: 3.7
Classifier: Programming Language :: Python :: 3.8
Requires-Dist: fast-pagerank (>=0.0.4,<0.0.5)
Requires-Dist: matplotlib (>=3.4.2,<4.0.0)
Requires-Dist: networkx (>=2.6.3,<3.0.0)
Requires-Dist: numpy (>=1.20.2,<2.0.0)
Requires-Dist: pandas (>=2.2.0,<3.0.0)
Requires-Dist: pyrdf2vec (>=0.2.3,<0.3.0)
Requires-Dist: rdflib (>=6.0.2,<7.0.0)
Requires-Dist: scikit-learn (>=0.24.2,<0.25.0) ; python_version >= "3.9"
Project-URL: Documentation, https://github.com/predict-idlab/VisCARS
Project-URL: Repository, https://github.com/predict-idlab/VisCARS
